README.md
image_transformer/__init__.py
image_transformer/commands/__init__.py
image_transformer/commands/helpers.py
image_transformer/commands/image_generator.py
image_transformer/commands/image_transformer.py
image_transformer/configurations.toml
image_transformer/constants.py
image_transformer/image_processors/__init__.py
image_transformer/image_processors/generic_grid_image_processor.py
image_transformer/image_processors/hexagonal_grid_image_processor.py
image_transformer/image_processors/square_grid_image_processor.py
image_transformer/image_processors/triangle_grid_image_processor.py
image_transformer/image_transformer.py
image_transformer/index.py
image_transformer/output_builders/__init__.py
image_transformer/output_builders/cairo_svg_output_builder.py
image_transformer/output_builders/generic_output_builder.py
image_transformer/output_builders/handmade_svg_output_builder.py
image_transformer/pixels_processors/__init__.py
image_transformer/pixels_processors/average_pixels_processor.py
image_transformer/pixels_processors/color_palette_based_pixel_processor.py
image_transformer/pixels_processors/generic_pixels_processor.py
image_transformer/pixels_processors/most_frequent_pixels_processor.py
image_transformer/pixels_processors/random_pixels_processor.py
image_transformer/utils/__init__.py
image_transformer/utils/click_color.py
image_transformer/utils/configurations_loader.py
image_transformer/utils/hex_to_rgb_color_converter.py
image_transformer/utils/loader.py
image_transformer-0.5.0.dist-info/METADATA
image_transformer-0.5.0.dist-info/WHEEL
image_transformer-0.5.0.dist-info/entry_points.txt
image_transformer-0.5.0.dist-info/RECORD
