Metadata-Version: 2.1
Name: image-transformer
Version: 0.5.0
Summary: A Python project for enhancing images using various processing techniques.
Home-page: https://raideno.github.io/image-transformer/
Keywords: image-processing,image-enhancement,image-transformer
Author: raiden
Author-email: nadirkichou@hotmail.fr
Maintainer: raiden
Maintainer-email: nadirkichou@hotmail.fr
Requires-Python: >=3.12,<4.0
Classifier: Programming Language :: Python :: 3
Classifier: Programming Language :: Python :: 3.12
Classifier: Programming Language :: Python :: 3.13
Requires-Dist: alive-progress (>=3.1.5,<4.0.0)
Requires-Dist: click (>=8.1.7,<9.0.0)
Requires-Dist: numpy (>=2.1.1,<3.0.0)
Requires-Dist: pillow (>=10.4.0,<11.0.0)
Requires-Dist: pycairo (>=1.27.0,<2.0.0)
Project-URL: Documentation, https://raideno.github.io/image-transformer/
Project-URL: Repository, https://github.com/raideno/image-transformer
